{
  "dataset": "synthetic_symbolic_insufficiency_path_response",
  "coarse_path_state_null_pass": true,
  "within_path_state_variation_pass": true,
  "latent_path_diversity_pass": true,
  "token_view_balance_pass": true,
  "path_length_balance_pass": true,
  "coarse_path_state_null_max_abs_mean": 0.0,
  "within_path_state_target_ranges": {
    "000": 0.270958,
    "001": 0.200238,
    "010": 0.213104,
    "011": 0.120706,
    "100": 0.174888,
    "101": 0.270958,
    "110": 0.120706,
    "111": 0.324954
  },
  "latent_path_group_counts": {
    "000": 4,
    "001": 4,
    "010": 4,
    "011": 4,
    "100": 4,
    "101": 4,
    "110": 4,
    "111": 4
  },
  "path_length_values": {
    "train": 2,
    "validation": 2,
    "test": 2
  },
  "feature_order": [
    "u_sector_magnitude_delta",
    "u_ordered_content_delta",
    "u_orientation_delta",
    "u_latent_transition_phase",
    "u_latent_transition_curvature",
    "v_sector_magnitude_delta",
    "v_ordered_content_delta",
    "v_orientation_delta",
    "v_latent_transition_phase",
    "v_latent_transition_curvature",
    "path_phase_mean",
    "path_phase_gap",
    "path_curvature_mean",
    "path_curvature_product",
    "path_declared_alignment",
    "path_declared_gap",
    "path_latent_declared_mix",
    "path_latent_cross_curvature"
  ],
  "coefficients": {
    "u_sector_magnitude_delta": -0.016103,
    "u_ordered_content_delta": 0.01404,
    "u_orientation_delta": -0.001238,
    "u_latent_transition_phase": -0.015065,
    "u_latent_transition_curvature": 0.018368,
    "v_sector_magnitude_delta": 0.02453,
    "v_ordered_content_delta": 0.056065,
    "v_orientation_delta": -0.037999,
    "v_latent_transition_phase": -0.01806,
    "v_latent_transition_curvature": -0.058091,
    "path_phase_mean": -0.016562,
    "path_phase_gap": 0.002995,
    "path_curvature_mean": -0.019862,
    "path_curvature_product": 0.005972,
    "path_declared_alignment": 0.07816,
    "path_declared_gap": -0.022253,
    "path_latent_declared_mix": -0.033597,
    "path_latent_cross_curvature": 0.052446
  },
  "intercept": 0.026308,
  "forbidden_inputs_absent": true,
  "mae": 0.052537,
  "rank_correlation": 0.313276,
  "calibration_slope": 0.413325,
  "bounded_feature_audit_pass": true,
  "forbidden_feature_family_absent_pass": true
}